ip_address/__init__.py
ip_address/ip_address.py
ip_address-1.4.0.dist-info/LICENSE
ip_address-1.4.0.dist-info/METADATA
ip_address-1.4.0.dist-info/WHEEL
ip_address-1.4.0.dist-info/top_level.txt
ip_address-1.4.0.dist-info/RECORD
