Metadata-Version: 2.1
Name: ip-address
Version: 1.4.0
Summary: A tracker that gets your public IP address
Home-page: https://github.com/dewittethomas/ip_address
License: MIT
Keywords: ip address ip-address public vpn dns ipv4 ipv6 isp location
Platform: UNKNOWN
Classifier: Programming Language :: Python :: 3
Classifier: Programming Language :: Python :: 3.6
Classifier: Programming Language :: Python :: 3.7
Classifier: Operating System :: OS Independent
Classifier: License :: OSI Approved :: MIT License
Requires-Dist: requests (>=2.22.0)
